LICENCE
README.md
setup.py
routput/_README.py
routput/__init__.py
routput/__main__.py
routput/_pickled.py
routput/routput.py
routput/templated_setup.py
routput.egg-info/PKG-INFO
routput.egg-info/SOURCES.txt
routput.egg-info/dependency_links.txt
routput.egg-info/top_level.txt