Metadata-Version: 2.1
Name: routput
Version: 0.9999
Summary: recursively searches for files based on their extensions starting from a specified directory. It can print the directory structure, include or exclude specific files, use syntax highlighting for output, and anonymize file paths for privacy.
Author: matrikater (Joel Watson)
License-File: LICENCE
